numpy_typing_compat/__init__.py
numpy_typing_compat/py.typed
numpy_typing_compat-20251206.2.2.dist-info/licenses/LICENSE
numpy_typing_compat-20251206.2.2.dist-info/WHEEL
numpy_typing_compat-20251206.2.2.dist-info/METADATA
numpy_typing_compat-20251206.2.2.dist-info/RECORD
