Metadata-Version: 2.4
Name: numpy-typing-compat
Version: 20251206.2.2
Summary: Static typing compatibility layer for older versions of NumPy
Keywords: numpy,optype,typing,compatibility
Author: Joren Hammudoglu
Author-email: Joren Hammudoglu <jhammudoglu@gmail.com>
License-Expression: BSD-3-Clause
License-File: LICENSE
Classifier: Development Status :: 4 - Beta
Classifier: Intended Audience :: Developers
Classifier: Operating System :: OS Independent
Classifier: Programming Language :: Python
Classifier: Programming Language :: Python :: 3
Classifier: Programming Language :: Python :: 3.10
Classifier: Programming Language :: Python :: 3.11
Classifier: Programming Language :: Python :: 3.12
Classifier: Programming Language :: Python :: 3.13
Classifier: Typing :: Typed
Requires-Dist: numpy>=2.2,<2.3
Requires-Python: >=3.10
Project-URL: Changelog, https://github.com/jorenham/numpy-typing-compat/releases
Project-URL: Issues, https://github.com/jorenham/numpy-typing-compat/issues
Project-URL: Repository, https://github.com/jorenham/numpy-typing-compat
